tuicub/__about__.py
tuicub/__init__.py
tuicub/__main__.py
tuicub/cli.py
tuicub/tuicub.py
tuicub/app/__init__.py
tuicub/app/controller.py
tuicub/app/module.py
tuicub/app/state.py
tuicub/app/status.py
tuicub/app/view.py
tuicub/app/viewmodel.py
tuicub/app/actions/__init__.py
tuicub/app/actions/remove_confirmation.py
tuicub/app/actions/set_confirmation.py
tuicub/common/__init__.py
tuicub/common/cache.py
tuicub/common/config.py
tuicub/common/logger.py
tuicub/common/models.py
tuicub/common/module.py
tuicub/common/schemas.py
tuicub/common/strings.py
tuicub/common/transitions.py
tuicub/common/utils.py
tuicub/common/confirmation/__init__.py
tuicub/common/confirmation/confirmation.py
tuicub/common/confirmation/factory.py
tuicub/common/confirmation/interactor.py
tuicub/common/confirmation/module.py
tuicub/common/confirmation/service.py
tuicub/common/events/__init__.py
tuicub/common/events/event.py
tuicub/common/events/factory.py
tuicub/common/events/handler.py
tuicub/common/events/module.py
tuicub/common/http/__init__.py
tuicub/common/http/auth_middleware.py
tuicub/common/http/client.py
tuicub/common/http/error_handler.py
tuicub/common/http/interactor.py
tuicub/common/http/module.py
tuicub/common/http/request.py
tuicub/common/keybinds/__init__.py
tuicub/common/keybinds/container.py
tuicub/common/screens/__init__.py
tuicub/common/screens/factory.py
tuicub/common/screens/name.py
tuicub/common/screens/root_view.py
tuicub/common/screens/tuicub_screen.py
tuicub/common/services/__init__.py
tuicub/common/services/alert_service.py
tuicub/common/services/auth_service.py
tuicub/common/services/exit_service.py
tuicub/common/services/module.py
tuicub/common/services/screen_size_service.py
tuicub/common/state/__init__.py
tuicub/common/state/module.py
tuicub/common/state/state.py
tuicub/common/state/store.py
tuicub/common/state/actions/__init__.py
tuicub/common/state/actions/add_gameroom_user.py
tuicub/common/state/actions/delete_gameroom.py
tuicub/common/state/actions/finish_game.py
tuicub-0.1.3.dist-info/METADATA
tuicub-0.1.3.dist-info/WHEEL
tuicub-0.1.3.dist-info/entry_points.txt
tuicub-0.1.3.dist-info/licenses/LICENSE
tuicub-0.1.3.dist-info/RECORD
