Metadata-Version: 2.1
Name: tuicub
Version: 0.1.3
Summary: Online multiplayer board game in your terminal.
Project-URL: Homepage, https://tuicub.com
Project-URL: Source, https://github.com/tom-bartk/tuicub
Project-URL: Issues, https://github.com/tom-bartk/tuicub/issues
Author-email: tombartk <tom.bartk@proton.me>
License-Expression: AGPL-3.0-or-later
License-File: LICENSE
Classifier: Development Status :: 4 - Beta
Classifier: Environment :: Console
Classifier: Intended Audience :: End Users/Desktop
Classifier: License :: OSI Approved :: GNU Affero General Public License v3 or later (AGPLv3+)
Classifier: Programming Language :: Python
Classifier: Programming Language :: Python :: 3.10
Classifier: Programming Language :: Python :: 3.11
Classifier: Programming Language :: Python :: 3.12
Classifier: Topic :: Games/Entertainment :: Board Games
Classifier: Typing :: Typed
Requires-Python: >=3.10
Requires-Dist: asockit
Requires-Dist: attrs==22.2.0
Requires-Dist: binpacking
Requires-Dist: cacheout
Requires-Dist: eventoolkit
Requires-Dist: httperactor
Requires-Dist: httpx
Requires-Dist: marshmallow
Requires-Dist: marshmallow-generic
Requires-Dist: more-itertools
Requires-Dist: pendulum==3.0.0b1
Requires-Dist: prompt-toolkit
Requires-Dist: pydepot
Requires-Dist: pyllot
Requires-Dist: structlog
Requires-Dist: typing-extensions
